pyXSteam/Constants.py
pyXSteam/IAPWS_R14.py
pyXSteam/IAPWS_R4.py
pyXSteam/RegionBorders.py
pyXSteam/RegionSelection.py
pyXSteam/Regions.py
pyXSteam/TransportProperties.py
pyXSteam/UnitConverter.py
pyXSteam/XSteam.py
pyXSteam/XSteam_HW.py
pyXSteam/__init__.py
pyxsteam-0.4.10.data/scripts/pyXSteamDemo.py
pyxsteam-0.4.10.dist-info/licenses/LICENSE.txt
pyxsteam-0.4.10.dist-info/METADATA
pyxsteam-0.4.10.dist-info/WHEEL
pyxsteam-0.4.10.dist-info/top_level.txt
pyxsteam-0.4.10.dist-info/zip-safe
pyxsteam-0.4.10.dist-info/RECORD
