Metadata-Version: 2.4
Name: pyXSteam
Version: 0.4.10
Summary: pyXSteam is a port of the Matlab/Excel Package XSteam
Home-page: https://github.com/drunsinn/pyXSteam
Author: drunsinn
Author-email: dr.unsinn@googlemail.com
Keywords: steam water ice XSteam
Classifier: Programming Language :: Python :: 3
Classifier: License :: OSI Approved :: GNU General Public License v2 (GPLv2)
Classifier: Operating System :: OS Independent
Classifier: Topic :: Scientific/Engineering :: Physics
Classifier: Development Status :: 4 - Beta
Requires-Python: >=3.4
License-File: LICENSE.txt
Dynamic: author
Dynamic: author-email
Dynamic: classifier
Dynamic: description
Dynamic: description-content-type
Dynamic: home-page
Dynamic: keywords
Dynamic: license-file
Dynamic: requires-python
Dynamic: summary
